scrawler/__init__.py
scrawler/attributes.py
scrawler/crawling.py
scrawler/data_extractors.py
scrawler/defaults.py
scrawler/scraping.py
scrawler/website.py
scrawler/backends/__init__.py
scrawler/backends/asyncio_backend.py
scrawler/backends/multithreading_backend.py
scrawler/utils/__init__.py
scrawler/utils/file_io_utils.py
scrawler/utils/general_utils.py
scrawler/utils/validation_utils.py
scrawler/utils/web_utils.py
scrawler-0.3.1.dist-info/LICENSE
scrawler-0.3.1.dist-info/METADATA
scrawler-0.3.1.dist-info/WHEEL
scrawler-0.3.1.dist-info/top_level.txt
scrawler-0.3.1.dist-info/RECORD
