Metadata-Version: 2.1
Name: scrawler
Version: 0.3.1
Summary: Tool for General Purpose Web Scraping and Crawling
Home-page: https://github.com/dglttr/scrawler
Author: Daniel Glatter
Author-email: d.glatter@outlook.com
License: MIT
Project-URL: Bug Tracker, https://github.com/dglttr/scrawler/issues
Project-URL: Documentation, https://scrawler.readthedocs.io/
Project-URL: Source Code, https://github.com/dglttr/scrawler
Keywords: Web Scraping,Crawling,asyncio,multithreading
Platform: UNKNOWN
Classifier: Programming Language :: Python :: 3
Classifier: License :: OSI Approved :: MIT License
Classifier: Operating System :: OS Independent
Requires-Python: >=3.6
License-File: LICENSE
Requires-Dist: beautifulsoup4 (>=4.9.1)
Requires-Dist: requests (>=2.24.0)
Requires-Dist: tld (>=0.12.5)
Requires-Dist: pandas (>=1.0.5)
Requires-Dist: python-dateutil (>=2.8.1)
Requires-Dist: setuptools (>=28.8.0)
Requires-Dist: aiohttp (>=3.7.3)
Requires-Dist: readability-lxml (>=0.8.1)
